intriniorealtime/__init__.py
intriniorealtime/equities_client.py
intriniorealtime/equities_replay_client.py
intriniorealtime/options_client.py
intriniorealtime-6.2.0.dist-info/licenses/LICENSE
intriniorealtime-6.2.0.dist-info/METADATA
intriniorealtime-6.2.0.dist-info/WHEEL
intriniorealtime-6.2.0.dist-info/top_level.txt
intriniorealtime-6.2.0.dist-info/RECORD
