Metadata-Version: 2.4
Name: intriniorealtime
Version: 6.2.0
Summary: Intrinio Python SDK for Real-Time Stock Prices
Home-page: https://intrinio.com
Download-URL: https://github.com/intrinio/intrinio-realtime-python-sdk/archive/v6.2.0.tar.gz
Author: Intrinio Python SDK for Real-Time Stock Prices
Author-email: success@intrinio.com
Keywords: realtime,stock prices,intrinio,stock market,stock data,financial
Classifier: Intended Audience :: Financial and Insurance Industry
Classifier: Topic :: Office/Business :: Financial :: Investment
Requires-Python: ~=3.10
License-File: LICENSE
Requires-Dist: requests>=2.26.0
Requires-Dist: websocket-client>=1.2.1
Requires-Dist: wsaccel>=0.6.3
Requires-Dist: intrinio-sdk>=6.26.0
Dynamic: author
Dynamic: author-email
Dynamic: classifier
Dynamic: description
Dynamic: description-content-type
Dynamic: download-url
Dynamic: home-page
Dynamic: keywords
Dynamic: license-file
Dynamic: requires-dist
Dynamic: requires-python
Dynamic: summary
